pynrose/__init__.py
pynrose/cli.py
pynrose/pynrose.py
pynrose-1.0.0.dist-info/METADATA
pynrose-1.0.0.dist-info/WHEEL
pynrose-1.0.0.dist-info/entry_points.txt
pynrose-1.0.0.dist-info/licenses/LICENSE
pynrose-1.0.0.dist-info/RECORD
