Metadata-Version: 2.1
Name: pynrose
Version: 1.0.0
Summary: P3 Penroser Tiling Generator
Project-URL: Homepage, https://github.com/jesusfreke/pynrose
Project-URL: Documentation, https://pynrose.readthedocs.io/
Author-email: Ben Gruver <jesusfreke@jesusfreke.com>
License-Expression: BSD-2-Clause
License-File: LICENSE
Keywords: de bruijn,penrose,tiling
Classifier: License :: OSI Approved :: BSD License
Classifier: Operating System :: OS Independent
Classifier: Programming Language :: Python :: 3
Classifier: Topic :: Scientific/Engineering :: Mathematics
Requires-Python: >=3.10
